{"Uncategorized": [], "Airtime & Data": ["Airtime Purchase", "Airtime", "Safaricom Airtime", "Buy Airtime", "Data Bundle"], "Bank Transfers": ["Transfer from Bank", "Bank Transfer", "To Bank Account", "From Bank", "IMBANK"], "Bill Payments": ["Pay Bill", "Bill Payment", "Utility Payment", "Electricity", "Water Bill", "Internet Bill"], "Business Payments": ["SmallBusiness", "Business Payment", "Merchant Payment", "Till Number", "Buy Goods"], "Family & Friends": ["Received from", "Sent to", "Family Support", "Friend", "Gift", "Help"], "Fuliza & Loans": ["Fuliza", "OverDraft", "OD Loan", "Loan Repayment", "Credit", "fuliza"], "Food & Dining": ["Restaurant", "Food", "Groceries", "Supermarket", "Takeaway"], "Transport": ["Matatu", "Taxi", "Uber", "Bolt", "Bus Fare", "Fuel"], "Shopping": ["Clothes", "Electronics", "Furniture", "Online Shopping", "Jumia"], "Entertainment": ["Movie", "Cinema", "Music", "Event", "Party"], "Savings": ["Savings", "Investment", "M-Shwari", "KCB M-Pesa", "Lock Savings"], "Salary & Income": ["Salary", "Payment Received", "Business Income", "Freelance", "Commission"], "Agent Transactions": ["Deposit at Agent", "Withdraw from Agent", "Agent Till", "Lipia na M-Pesa"], "Charges & Fees": ["Transaction Fee", "Service Charge", "Withdrawal Fee", "Transfer Charge", "Penalty"]}